cvertools/__init__.py
cvertools/baseml.py
asrertools-0.0.0.dist-info/LICENSE
asrertools-0.0.0.dist-info/METADATA
asrertools-0.0.0.dist-info/WHEEL
asrertools-0.0.0.dist-info/top_level.txt
asrertools-0.0.0.dist-info/RECORD
